Workbook

Sheet 00_README

Sheet 01_RAW_DATA
A1: Order_ID | B1: Order_Date | C1: Region | D1: Channel | E1: Product_Category | F1: Shoe_Model | G1: Units_Sold | H1: Unit_Price | I1: Revenue
A2: 1001 | B2: 45413 | C2: East | D2: DTC | E2: Running | F2: AeroRun 2 | G2: 2 | H2: 140 | I2: =G2*H2 -> 280
A3: 1002 | B3: 45444 | C3: West | D3: Retail | E3: Running | F3: CloudStride | G3: 1 | H3: 135 | I3: =G3*H3 -> 135
A4: 1003 | B4: 45474 | C4: Midwest | D4: DTC | E4: Training | F4: Powerlift | G4: 3 | H4: 120 | I4: =G4*H4 -> 360
A5: 1004 | B5: 45505 | C5: South | D5: Retail | E5: Lifestyle | F5: StreetFlow | G5: 2 | H5: 95 | I5: =G5*H5 -> 190
A6: 1005 | B6: 45536 | C6: East | D6: DTC | E6: Lifestyle | F6: DailyMove | G6: 1 | H6: 90 | I6: =G6*H6 -> 90
A7: 1006 | B7: 45566 | C7: West | D7: DTC | E7: Running | F7: AeroRun 2 | G7: 3 | H7: 145 | I7: =G7*H7 -> 435
A8: 1007 | B8: 45597 | C8: East | D8: Retail | E8: Running | F8: CloudStride | G8: 2 | H8: 130 | I8: =G8*H8 -> 260
A9: 1008 | B9: 45627 | C9: Midwest | D9: DTC | E9: Lifestyle | F9: DailyMove | G9: 2 | H9: 95 | I9: =G9*H9 -> 190
A10: 1009 | B10: 45304 | C10: South | D10: Retail | E10: Training | F10: FlexTrainer | G10: 1 | H10: 115 | I10: =G10*H10 -> 115
A11: 1010 | B11: 45305 | C11: West | D11: Retail | E11: Lifestyle | F11: StreetFlow | G11: 3 | H11: 100 | I11: =G11*H11 -> 300
A12: 1011 | B12: 45306 | C12: East | D12: DTC | E12: Training | F12: Powerlift | G12: 2 | H12: 125 | I12: =G12*H12 -> 250
A13: 1012 | B13: 45307 | C13: Midwest | D13: Retail | E13: Running | F13: AeroRun 2 | G13: 1 | H13: 135 | I13: =G13*H13 -> 135
... A15: 1014 | B15: 45309 | C15: West | D15: DTC | E15: Training | F15: FlexTrainer | G15: 2 | H15: 120 | I15: =G15*H15 -> 240

Sheet 02_CLEAN_DATA
A1: Order_ID | B1: Order_Date | C1: Region | D1: Channel | E1: Product_Category | F1: Shoe_Model | G1: Units_Sold | H1: Unit_Price | I1: Revenue | J1: Year | K1: Month | L1: Quarter
A2: 1001 | B2: 45413 | C2: East | D2: DTC | E2: Running | F2: AeroRun 2 | G2: 2 | H2: 140 | I2: =G2*H2 -> 280 | J2: =YEAR(tbl_clean[[#This Row],[Order_Date]]) -> 2024 | K2: =TEXT(tbl_clean[[#This Row],[Order_Date]],"yyyy-mm") -> 2024-05 | L2: ="Q"&ROUNDUP(MONTH(tbl_clean[[#This Row],[Order_Date]])/3,0)&" "&YEAR(tbl_clean[[#This Row],[Order_Date]]) -> Q2 2024
A3: 1002 | B3: 45444 | C3: West | D3: Retail | E3: Running | F3: CloudStride | G3: 1 | H3: 135 | I3: =G3*H3 -> 135 | J3: =YEAR(tbl_clean[[#This Row],[Order_Date]]) -> 2024 | K3: =TEXT(tbl_clean[[#This Row],[Order_Date]],"yyyy-mm") -> 2024-06 | L3: ="Q"&ROUNDUP(MONTH(tbl_clean[[#This Row],[Order_Date]])/3,0)&" "&YEAR(tbl_clean[[#This Row],[Order_Date]]) -> Q2 2024
A4: 1003 | B4: 45474 | C4: Midwest | D4: DTC | E4: Training | F4: Powerlift | G4: 3 | H4: 120 | I4: =G4*H4 -> 360 | J4: =YEAR(tbl_clean[[#This Row],[Order_Date]]) -> 2024 | K4: =TEXT(tbl_clean[[#This Row],[Order_Date]],"yyyy-mm") -> 2024-07 | L4: ="Q"&ROUNDUP(MONTH(tbl_clean[[#This Row],[Order_Date]])/3,0)&" "&YEAR(tbl_clean[[#This Row],[Order_Date]]) -> Q3 2024
A5: 1004 | B5: 45505 | C5: South | D5: Retail | E5: Lifestyle | F5: StreetFlow | G5: 2 | H5: 95 | I5: =G5*H5 -> 190 | J5: =YEAR(tbl_clean[[#This Row],[Order_Date]]) -> 2024 | K5: =TEXT(tbl_clean[[#This Row],[Order_Date]],"yyyy-mm") -> 2024-08 | L5: ="Q"&ROUNDUP(MONTH(tbl_clean[[#This Row],[Order_Date]])/3,0)&" "&YEAR(tbl_clean[[#This Row],[Order_Date]]) -> Q3 2024
A6: 1005 | B6: 45536 | C6: East | D6: DTC | E6: Lifestyle | F6: DailyMove | G6: 1 | H6: 90 | I6: =G6*H6 -> 90 | J6: =YEAR(tbl_clean[[#This Row],[Order_Date]]) -> 2024 | K6: =TEXT(tbl_clean[[#This Row],[Order_Date]],"yyyy-mm") -> 2024-09 | L6: ="Q"&ROUNDUP(MONTH(tbl_clean[[#This Row],[Order_Date]])/3,0)&" "&YEAR(tbl_clean[[#This Row],[Order_Date]]) -> Q3 2024
A7: 1006 | B7: 45566 | C7: West | D7: DTC | E7: Running | F7: AeroRun 2 | G7: 3 | H7: 145 | I7: =G7*H7 -> 435 | J7: =YEAR(tbl_clean[[#This Row],[Order_Date]]) -> 2024 | K7: =TEXT(tbl_clean[[#This Row],[Order_Date]],"yyyy-mm") -> 2024-10 | L7: ="Q"&ROUNDUP(MONTH(tbl_clean[[#This Row],[Order_Date]])/3,0)&" "&YEAR(tbl_clean[[#This Row],[Order_Date]]) -> Q4 2024
A8: 1007 | B8: 45597 | C8: East | D8: Retail | E8: Running | F8: CloudStride | G8: 2 | H8: 130 | I8: =G8*H8 -> 260 | J8: =YEAR(tbl_clean[[#This Row],[Order_Date]]) -> 2024 | K8: =TEXT(tbl_clean[[#This Row],[Order_Date]],"yyyy-mm") -> 2024-11 | L8: ="Q"&ROUNDUP(MONTH(tbl_clean[[#This Row],[Order_Date]])/3,0)&" "&YEAR(tbl_clean[[#This Row],[Order_Date]]) -> Q4 2024
A9: 1008 | B9: 45627 | C9: Midwest | D9: DTC | E9: Lifestyle | F9: DailyMove | G9: 2 | H9: 95 | I9: =G9*H9 -> 190 | J9: =YEAR(tbl_clean[[#This Row],[Order_Date]]) -> 2024 | K9: =TEXT(tbl_clean[[#This Row],[Order_Date]],"yyyy-mm") -> 2024-12 | L9: ="Q"&ROUNDUP(MONTH(tbl_clean[[#This Row],[Order_Date]])/3,0)&" "&YEAR(tbl_clean[[#This Row],[Order_Date]]) -> Q4 2024
A10: 1009 | B10: 45304 | C10: South | D10: Retail | E10: Training | F10: FlexTrainer | G10: 1 | H10: 115 | I10: =G10*H10 -> 115 | J10: =YEAR(tbl_clean[[#This Row],[Order_Date]]) -> 2024 | K10: =TEXT(tbl_clean[[#This Row],[Order_Date]],"yyyy-mm") -> 2024-01 | L10: ="Q"&ROUNDUP(MONTH(tbl_clean[[#This Row],[Order_Date]])/3,0)&" "&YEAR(tbl_clean[[#This Row],[Order_Date]]) -> Q1 2024
A11: 1010 | B11: 45305 | C11: West | D11: Retail | E11: Lifestyle | F11: StreetFlow | G11: 3 | H11: 100 | I11: =G11*H11 -> 300 | J11: =YEAR(tbl_clean[[#This Row],[Order_Date]]) -> 2024 | K11: =TEXT(tbl_clean[[#This Row],[Order_Date]],"yyyy-mm") -> 2024-01 | L11: ="Q"&ROUNDUP(MONTH(tbl_clean[[#This Row],[Order_Date]])/3,0)&" "&YEAR(tbl_clean[[#This Row],[Order_Date]]) -> Q1 2024
A12: 1011 | B12: 45306 | C12: East | D12: DTC | E12: Training | F12: Powerlift | G12: 2 | H12: 125 | I12: =G12*H12 -> 250 | J12: =YEAR(tbl_clean[[#This Row],[Order_Date]]) -> 2024 | K12: =TEXT(tbl_clean[[#This Row],[Order_Date]],"yyyy-mm") -> 2024-01 | L12: ="Q"&ROUNDUP(MONTH(tbl_clean[[#This Row],[Order_Date]])/3,0)&" "&YEAR(tbl_clean[[#This Row],[Order_Date]]) -> Q1 2024
A13: 1012 | B13: 45307 | C13: Midwest | D13: Retail | E13: Running | F13: AeroRun 2 | G13: 1 | H13: 135 | I13: =G13*H13 -> 135 | J13: =YEAR(tbl_clean[[#This Row],[Order_Date]]) -> 2024 | K13: =TEXT(tbl_clean[[#This Row],[Order_Date]],"yyyy-mm") -> 2024-01 | L13: ="Q"&ROUNDUP(MONTH(tbl_clean[[#This Row],[Order_Date]])/3,0)&" "&YEAR(tbl_clean[[#This Row],[Order_Date]]) -> Q1 2024
... A15: 1014 | B15: 45309 | C15: West | D15: DTC | E15: Training | F15: FlexTrainer | G15: 2 | H15: 120 | I15: =G15*H15 -> 240 | J15: =YEAR(tbl_clean[[#This Row],[Order_Date]]) -> 2024 | K15: =TEXT(tbl_clean[[#This Row],[Order_Date]],"yyyy-mm") -> 2024-01 | L15: ="Q"&ROUNDUP(MONTH(tbl_clean[[#This Row],[Order_Date]])/3,0)&" "&YEAR(tbl_clean[[#This Row],[Order_Date]]) -> Q1 2024

Sheet 03_KPI_SUMMARY
A2: Total Revenue | B2: =SUM(tbl_clean[Revenue]) -> 3260
A3: Total Units Sold | B3: =SUM(tbl_clean[Units_Sold]) -> 27
A4: Orders | B4: =COUNTA(tbl_clean[Order_ID]) -> 14
A5: AOV (Avg Order Value) | B5: =B2/B4 -> 232.85714
A7: Region | B7: Revenue | D7: Category | E7: Revenue
A8: East | B8: =SUMIFS(tbl_clean[Revenue],tbl_clean[Region],A8) -> 880 | D8: Running | E8: =SUMIFS(tbl_clean[Revenue],tbl_clean[Product_Category],D8) -> 1525
A9: West | B9: =SUMIFS(tbl_clean[Revenue],tbl_clean[Region],A9) -> 1110 | D9: Training | E9: =SUMIFS(tbl_clean[Revenue],tbl_clean[Product_Category],D9) -> 965
A10: Midwest | B10: =SUMIFS(tbl_clean[Revenue],tbl_clean[Region],A10) -> 685 | D10: Lifestyle | E10: =SUMIFS(tbl_clean[Revenue],tbl_clean[Product_Category],D10) -> 770
A11: South | B11: =SUMIFS(tbl_clean[Revenue],tbl_clean[Region],A11) -> 585
A14: Month | B14: Revenue
A15: 2024-01 | B15: =SUMIFS('02_CLEAN_DATA'!$I:$I,'02_CLEAN_DATA'!$K:$K,$A15) -> 1320
A16: 2024-05 | B16: =SUMIFS('02_CLEAN_DATA'!$I:$I,'02_CLEAN_DATA'!$K:$K,$A16) -> 280
A17: 2024-06 | B17: =SUMIFS('02_CLEAN_DATA'!$I:$I,'02_CLEAN_DATA'!$K:$K,$A17) -> 135
A18: 2024-07 | B18: =SUMIFS('02_CLEAN_DATA'!$I:$I,'02_CLEAN_DATA'!$K:$K,$A18) -> 360
A19: 2024-08 | B19: =SUMIFS('02_CLEAN_DATA'!$I:$I,'02_CLEAN_DATA'!$K:$K,$A19) -> 190
A20: 2024-09 | B20: =SUMIFS('02_CLEAN_DATA'!$I:$I,'02_CLEAN_DATA'!$K:$K,$A20) -> 90
A21: 2024-10 | B21: =SUMIFS('02_CLEAN_DATA'!$I:$I,'02_CLEAN_DATA'!$K:$K,$A21) -> 435
A22: 2024-11 | B22: =SUMIFS('02_CLEAN_DATA'!$I:$I,'02_CLEAN_DATA'!$K:$K,$A22) -> 260
A23: 2024-12 | B23: =SUMIFS('02_CLEAN_DATA'!$I:$I,'02_CLEAN_DATA'!$K:$K,$A23) -> 190

Sheet 04_PIVOT_ANALYSIS
A1: Revenue By Region | E1: Revenue by Product Category | I1: Monthly Revenue Trend
A2: Region | B2: Sum of Revenue | E2: Category | F2: Sum of Revenue | I2: Month | J2: Sum of Revenue
A3: East | B3: 880 | E3: Lifestyle | F3: 770 | I3: 2024-01 | J3: 1320
A4: Midwest | B4: 685 | E4: Running | F4: 1525 | I4: 2024-05 | J4: 280
A5: South | B5: 585 | E5: Training | F5: 965 | I5: 2024-06 | J5: 135
A6: West | B6: 1110 | E6: Grand Total | F6: 3260 | I6: 2024-07 | J6: 360
A7: Grand Total | B7: 3260 | I7: 2024-08 | J7: 190
I8: 2024-09 | J8: 90
I9: 2024-10 | J9: 435
I10: 2024-11 | J10: 260
I11: 2024-12 | J11: 190
I12: Grand Total | J12: 3260

Sheet 05_DASHBOARD
A1: Footwear Sales Performance Dashboard
A2: Execuite Summary | 2024
A4: Total Revenue | B4: Units Sold | C4: Orders | D4: Avg Order Value
A5: ='03_KPI_SUMMARY'!B2 -> 3260 | B5: ='03_KPI_SUMMARY'!B3 -> 27 | C5: ='03_KPI_SUMMARY'!B4 -> 14 | D5: ='03_KPI_SUMMARY'!B5 -> 232.85714

Sheet 06_INSIGHTS_NOTES
A1: Title:
A2: Footwear Sales Performance Analysis (2024)
A4: Business Context:
A5: This analysis evaluates a footwear brand’s 2024 sales performance to identify key revenue drivers, underperforming regions, and actionable growth opportunities.
A7: Executive Summary:
A8: In 2024, total revenue reached $3,260 across 14 orders and 27 units sold, resulting in an average order value (AOV) of $232.86. Revenue performance varied significantly by region and product category, with the West region and Running category emerging as the primary revenue drivers. These patterns highlight clear opportunities to reinforce high-performing segments while addressing underperforming regions.
A10: Key Insights
A11: The West region generated the highest revenue at $1,110, followed by the East at $880. The Midwest ($685) and South ($585) underperformed, indicating potential gaps in market penetration or regional demand.
A13: Are sales trending up or down over time?
A15: KPIs Tracked:
A16: These KPIs provide a high-level view of sales efficiency, demand distribution, and revenue concentration across regions and product categories.
A18: Total Revenue
... A53: Total Revenue: $3,260 | Total Units Sold: 27 | Orders: 14 | AOV: $232.86
